hashwrap/__init__.py
hashwrap/fortran_arrays.toml
hashwrap/hash.toml
hashwrap/hash_utils.py
hashwrap/hashwrapper.py
hashwrap/libhashpy.cpython-310-darwin.so
hashwrap/read_phase_formats.py
hashwrap/read_sp_ratios.py
hashwrap/docs/HASH_manual_v1.2.pdf
hashwrap/sample/example1.toml
hashwrap/sample/example2.toml
hashwrap/sample/example3.toml
hashwrap/sample/hash.toml
hashwrap/sample/data/example1.inp
hashwrap/sample/data/example1.out
hashwrap/sample/data/example1.out2
hashwrap/sample/data/example2.inp
hashwrap/sample/data/example2.out
hashwrap/sample/data/example2.out2
hashwrap/sample/data/example3.inp
hashwrap/sample/data/example3.out
hashwrap/sample/data/example4.inp
hashwrap/sample/data/example4.out
hashwrap/sample/data/example4.out2
hashwrap/sample/data/example5.inp
hashwrap/sample/data/example5.out
hashwrap/sample/data/example5.out2
hashwrap/sample/data/north1.phase
hashwrap/sample/data/north2.phase
hashwrap/sample/data/north3.amp
hashwrap/sample/data/north3.statcor
hashwrap/sample/data/north4.phase
hashwrap/sample/data/north5.simul
hashwrap/sample/data/scsn.reverse
hashwrap/sample/data/scsn.stations
hashwrap/sample/data/scsn.stations_5char
hashwrap/sample/data/vel.inc
hashwrap/sample/data/vz.kds
hashwrap/sample/data/vz.kds_orig
hashwrap/sample/data/vz.lab1
hashwrap/sample/data/vz.north
hashwrap/sample/data/vz.pickema1
hashwrap/sample/data/vz.pickema2
hashwrap/sample/data/vz.pickema3
hashwrap/sample/data/vz.sgm1
hashwrap/sample/data/vz.socal
hashwrap/sample/data/vz.vb1
hashwrap/src/Makefile
hashwrap/src/fmamp_subs.f
hashwrap/src/fmech_subs.f
hashwrap/src/param.inc
hashwrap/src/pol_subs.f
hashwrap/src/rot.inc
hashwrap/src/station_subs.f
hashwrap/src/station_subs_5char.f
hashwrap/src/uncert_subs.f
hashwrap/src/util_subs.f
hashwrap/src/vel.inc
hashwrap/src/vel_subs.f
hashwrap/src/vel_subs2.f
hashwrap-0.0.3.dist-info/METADATA
hashwrap-0.0.3.dist-info/WHEEL
hashwrap-0.0.3.dist-info/top_level.txt
hashwrap-0.0.3.dist-info/RECORD
